spec2vec/Document.py
spec2vec/Spec2Vec.py
spec2vec/SpectrumDocument.py
spec2vec/SpectrumDocumentWithLosses.py
spec2vec/__init__.py
spec2vec/__version__.py
spec2vec/logging_functions.py
spec2vec/model_building.py
spec2vec/serialization/__init__.py
spec2vec/serialization/model_exporting.py
spec2vec/serialization/model_importing.py
spec2vec/utils.py
spec2vec/vector_operations.py
spec2vec-0.9.1.dist-info/METADATA
spec2vec-0.9.1.dist-info/WHEEL
spec2vec-0.9.1.dist-info/licenses/LICENSE
spec2vec-0.9.1.dist-info/RECORD
