Metadata-Version: 2.4
Name: spec2vec
Version: 0.9.1
Summary: Word2Vec based similarity measure of mass spectrometry data.
License: Apache Software License 2.0
License-File: LICENSE
Keywords: word2vec,mass spectrometry,fuzzy matching,fuzzy search
Author: Florian Huber
Author-email: florian.huber@hs-duesseldorf.de
Requires-Python: >=3.10,<3.14
Classifier: License :: Other/Proprietary License
Classifier: Programming Language :: Python :: 3
Classifier: Programming Language :: Python :: 3.10
Classifier: Programming Language :: Python :: 3.11
Classifier: Programming Language :: Python :: 3.12
Classifier: Programming Language :: Python :: 3.13
Requires-Dist: gensim (>=4.4.0,<5.0.0)
Requires-Dist: matchms (>=0.27.0)
Requires-Dist: tqdm (>=4.66.5,<5.0.0)
Project-URL: Repository, https://github.com/iomega/spec2vec
